README.md
setup.cfg
setup.py
pysecurebox/__init__.py
pysecurebox/securebox.py
pysecurebox.egg-info/PKG-INFO
pysecurebox.egg-info/SOURCES.txt
pysecurebox.egg-info/dependency_links.txt
pysecurebox.egg-info/requires.txt
pysecurebox.egg-info/top_level.txt