Metadata-Version: 1.1
Name: pysecurebox
Version: 1.0.0
Summary: securebox-py (SecureBox for Python) is a lightweight package to create and manage consistent, encrypted and authenticated files.
Home-page: https://github.com/CoffeePerry/securebox-py
Author: Simone Perini
Author-email: perinisimone98@gmail.com
License: MIT
Download-URL: https://github.com/CoffeePerry/securebox-py/archive/1.0.0.tar.gz
Keywords: security,files,encryption,authentication
Platform: UNKNOWN
Classifier: Development Status :: 5 - Production/Stable
Classifier: Intended Audience :: Developers
Classifier: Topic :: Security :: Cryptography
Classifier: License :: OSI Approved :: MIT License
Classifier: Programming Language :: Python :: 3
